msl_internal/__init__.py
msl_internal/_base_client.py
msl_internal/_client.py
msl_internal/_compat.py
msl_internal/_constants.py
msl_internal/_exceptions.py
msl_internal/_files.py
msl_internal/_models.py
msl_internal/_qs.py
msl_internal/_resource.py
msl_internal/_response.py
msl_internal/_streaming.py
msl_internal/_types.py
msl_internal/_version.py
msl_internal/py.typed
msl_internal/_utils/__init__.py
msl_internal/_utils/_logs.py
msl_internal/_utils/_proxy.py
msl_internal/_utils/_reflection.py
msl_internal/_utils/_resources_proxy.py
msl_internal/_utils/_streams.py
msl_internal/_utils/_sync.py
msl_internal/_utils/_transform.py
msl_internal/_utils/_typing.py
msl_internal/_utils/_utils.py
msl_internal/resources/__init__.py
msl_internal/resources/chat/__init__.py
msl_internal/resources/chat/chat.py
msl_internal/resources/chat/completions.py
msl_internal/types/__init__.py
msl_internal/types/completion_message_param.py
msl_internal/types/create_chat_completion_response_stream_chunk.py
msl_internal/types/message_image_content_item_param.py
msl_internal/types/message_text_content_item_param.py
msl_internal/types/system_message_param.py
msl_internal/types/tool_response_message_param.py
msl_internal/types/user_message_param.py
msl_internal/types/chat/__init__.py
msl_internal/types/chat/completion_create_params.py
msl_internal/types/chat/completion_create_response.py
msl_internal-0.0.1.dist-info/METADATA
msl_internal-0.0.1.dist-info/WHEEL
msl_internal-0.0.1.dist-info/licenses/LICENSE
msl_internal-0.0.1.dist-info/RECORD
